colorwsap/__init__.py
colorwsap/core.py
colorwsap-0.1.3.dist-info/METADATA
colorwsap-0.1.3.dist-info/WHEEL
colorwsap-0.1.3.dist-info/top_level.txt
colorwsap-0.1.3.dist-info/RECORD
