Metadata-Version: 2.4
Name: colorwsap
Version: 0.1.3
Summary: Swap PNG logo colors easily by name or RGB
Author: Karan Bedi
Requires-Python: >=3.6
Requires-Dist: opencv-python
Requires-Dist: numpy
Dynamic: author
Dynamic: description
Dynamic: description-content-type
Dynamic: requires-dist
Dynamic: requires-python
Dynamic: summary
